examples/advanced_hooks/app.py
examples/basic_usage/app.py
examples/distributed_locking/app.py
examples/full_featured/app.py
examples/health_monitoring/app.py
examples/opentelemetry_integration/app.py
examples/retry_and_timeout/app.py
fastapi_crons/__init__.py
fastapi_crons/cli.py
fastapi_crons/config.py
fastapi_crons/endpoints.py
fastapi_crons/hooks.py
fastapi_crons/job.py
fastapi_crons/locking.py
fastapi_crons/py.typed
fastapi_crons/retry.py
fastapi_crons/runner.py
fastapi_crons/scheduler.py
fastapi_crons/state.py
fastapi_crons/telemetry.py
fastapi_crons-2.1.1.dist-info/licenses/LICENSE
scripts/setup_dev_env.py
tests/__init__.py
tests/conftest.py
tests/test_config.py
tests/test_hooks.py
tests/test_integration.py
tests/test_job.py
tests/test_scheduler.py
tests/test_state_backend.py
fastapi_crons-2.1.1.dist-info/METADATA
fastapi_crons-2.1.1.dist-info/WHEEL
fastapi_crons-2.1.1.dist-info/top_level.txt
fastapi_crons-2.1.1.dist-info/RECORD
