Metadata-Version: 2.4
Name: fastapi-crons
Version: 2.1.1
Summary: Cron scheduling extension for FastAPI with decorators, async support, Hooks, CLI, and SQLite job tracking.
Author-email: Mehar Umar <contact@meharumar.codes>
License: MIT License
Project-URL: Homepage, https://github.com/me-umar/fastapi-crons
Project-URL: Documentation, https://crons.meharumar.codes
Keywords: fastapi,cron,scheduler,background jobs,tasks,async crons,fastapi crons,crons
Requires-Python: >=3.10
License-File: LICENSE
Requires-Dist: fastapi>=0.100
Requires-Dist: croniter>=1.3.0
Requires-Dist: aiosqlite>=0.18.0
Requires-Dist: typer[all]>=0.9.0
Requires-Dist: rich
Requires-Dist: redis
Requires-Dist: pydantic>=2.0.0
Requires-Dist: aiohttp
Provides-Extra: dev
Requires-Dist: pytest>=7.0.0; extra == "dev"
Requires-Dist: pytest-asyncio>=0.21.0; extra == "dev"
Requires-Dist: pytest-cov>=4.0.0; extra == "dev"
Requires-Dist: ruff>=0.1.0; extra == "dev"
Requires-Dist: mypy>=1.0.0; extra == "dev"
Requires-Dist: types-aiofiles; extra == "dev"
Requires-Dist: types-redis; extra == "dev"
Requires-Dist: build>=1.0.0; extra == "dev"
Requires-Dist: twine>=4.0.0; extra == "dev"
Provides-Extra: otel
Requires-Dist: opentelemetry-api>=1.0.0; extra == "otel"
Requires-Dist: opentelemetry-sdk>=1.0.0; extra == "otel"
Dynamic: license-file
